nerdcolor/__init__.py
nerdcolor/__main__.py
nerdcolor/nerdcolor.py
Nerd_Color-0.1.0.dist-info/LICENSE
Nerd_Color-0.1.0.dist-info/METADATA
Nerd_Color-0.1.0.dist-info/WHEEL
Nerd_Color-0.1.0.dist-info/entry_points.txt
Nerd_Color-0.1.0.dist-info/top_level.txt
Nerd_Color-0.1.0.dist-info/RECORD
