Metadata-Version: 2.1
Name: Nerd-Color
Version: 0.1.0
Summary: A simple CLI colorizer.
Home-page: https://github.com/0xHaru/Nerd-Color
Author: 0xHaru
Author-email: 0xharu.git@gmail.com
License: GPLv3
Project-URL: Bug Tracker, https://github.com/0xHaru/Nerd-Color/issues
Keywords: color colour colorscheme terminal
Platform: UNKNOWN
Classifier: Programming Language :: Python :: 3
Classifier: Programming Language :: Python :: 3.6
Classifier: Programming Language :: Python :: 3.7
Classifier: Programming Language :: Python :: 3.8
Classifier: Programming Language :: Python :: 3.9
Classifier: Programming Language :: Python :: 3.10
Classifier: Operating System :: POSIX :: Linux
Classifier: License :: OSI Approved :: GNU General Public License v3 (GPLv3)
Requires-Python: >=3.6
License-File: LICENSE
